setup.py
kenu_ai_voice/__init__.py
kenu_ai_voice.egg-info/PKG-INFO
kenu_ai_voice.egg-info/SOURCES.txt
kenu_ai_voice.egg-info/dependency_links.txt
kenu_ai_voice.egg-info/requires.txt
kenu_ai_voice.egg-info/top_level.txt