Metadata-Version: 2.1
Name: kenu-ai-voice
Version: 0.0.1
Summary: Python Voice Chat AI
Author: r4isy
Author-email: r4isy@kenucheck.xyz
